ndtk/__init__.py
ndtk-0.0.1.1.dist-info/DESCRIPTION.rst
ndtk-0.0.1.1.dist-info/METADATA
ndtk-0.0.1.1.dist-info/RECORD
ndtk-0.0.1.1.dist-info/WHEEL
ndtk-0.0.1.1.dist-info/metadata.json
ndtk-0.0.1.1.dist-info/top_level.txt
