Metadata-Version: 2.0
Name: ndtk
Version: 0.0.1.1
Summary: Novelty Detection Toolkit
Home-page: https://gitlab.com/georgethrax/ndtk
Author: georgethrax
Author-email: pyruby@163.com
License: UNKNOWN
Platform: UNKNOWN
Classifier: Programming Language :: Python :: 2.7
Classifier: Programming Language :: Python :: 3.6
Classifier: Programming Language :: Python :: 3.7
Classifier: License :: OSI Approved :: MIT License
Classifier: Operating System :: OS Independent
